{
  "best_global_step": null,
  "best_metric": null,
  "best_model_checkpoint": null,
  "epoch": 15.0,
  "eval_steps": 15.0,
  "global_step": 30,
  "is_hyper_param_search": false,
  "is_local_process_zero": true,
  "is_world_process_zero": true,
  "log_history": [
    {
      "epoch": 0.5,
      "grad_norm": 41.422420501708984,
      "learning_rate": 2.5e-05,
      "logits/chosen": -0.22462975978851318,
      "logits/rejected": 0.3398582935333252,
      "logps/chosen": -384.92059326171875,
      "logps/rejected": -82.70263671875,
      "loss": 1.0817519426345825,
      "nll_loss": 3.8860480785369873,
      "rewards/accuracies": 0.0,
      "rewards/chosen": 0.0,
      "rewards/margins": 0.0,
      "rewards/rejected": 0.0,
      "step": 1
    },
    {
      "epoch": 1.0,
      "grad_norm": 42.63987731933594,
      "learning_rate": 5e-05,
      "logits/chosen": -0.2992066442966461,
      "logits/rejected": -0.1184350997209549,
      "logps/chosen": -395.36773681640625,
      "logps/rejected": -105.85407257080078,
      "loss": 1.0794453620910645,
      "nll_loss": 3.8629817962646484,
      "rewards/accuracies": 0.0,
      "rewards/chosen": 0.0,
      "rewards/margins": 0.0,
      "rewards/rejected": 0.0,
      "step": 2
    },
    {
      "epoch": 1.5,
      "grad_norm": 7.553483009338379,
      "learning_rate": 4.991461232516675e-05,
      "logits/chosen": -0.10202167183160782,
      "logits/rejected": 0.10234220325946808,
      "logps/chosen": -373.6258544921875,
      "logps/rejected": -90.15179443359375,
      "loss": 0.45817533135414124,
      "nll_loss": 3.6732964515686035,
      "rewards/accuracies": 1.0,
      "rewards/chosen": 2.248152256011963,
      "rewards/margins": 2.524315595626831,
      "rewards/rejected": -0.27616357803344727,
      "step": 3
    },
    {
      "epoch": 2.0,
      "grad_norm": 1.4981259107589722,
      "learning_rate": 4.965903258506806e-05,
      "logits/chosen": 0.1949131339788437,
      "logits/rejected": 0.6677072644233704,
      "logps/chosen": -343.8343505859375,
      "logps/rejected": -105.30181884765625,
      "loss": 0.3606632649898529,
      "nll_loss": 3.4526586532592773,
      "rewards/accuracies": 1.0,
      "rewards/chosen": 4.0346550941467285,
      "rewards/margins": 4.448182106018066,
      "rewards/rejected": -0.4135269522666931,
      "step": 4
    },
    {
      "epoch": 2.5,
      "grad_norm": 0.5025506615638733,
      "learning_rate": 4.923500664848326e-05,
      "logits/chosen": -0.05627884715795517,
      "logits/rejected": 0.20331113040447235,
      "logps/chosen": -248.99923706054688,
      "logps/rejected": -98.11944580078125,
      "loss": 0.25590312480926514,
      "nll_loss": 2.553950786590576,
      "rewards/accuracies": 1.0,
      "rewards/chosen": 6.89863920211792,
      "rewards/margins": 8.663246154785156,
      "rewards/rejected": -1.7646064758300781,
      "step": 5
    },
    {
      "epoch": 3.0,
      "grad_norm": 0.4751606583595276,
      "learning_rate": 4.864543104251587e-05,
      "logits/chosen": 1.1758580207824707,
      "logits/rejected": 1.5043249130249023,
      "logps/chosen": -358.2339172363281,
      "logps/rejected": -117.09266662597656,
      "loss": 0.34827831387519836,
      "nll_loss": 3.4822745323181152,
      "rewards/accuracies": 1.0,
      "rewards/chosen": 10.406876564025879,
      "rewards/margins": 11.30781078338623,
      "rewards/rejected": -0.9009340405464172,
      "step": 6
    },
    {
      "epoch": 3.5,
      "grad_norm": 0.38437461853027344,
      "learning_rate": 4.789433316637644e-05,
      "logits/chosen": 0.9264091849327087,
      "logits/rejected": 1.276641607284546,
      "logps/chosen": -284.1270446777344,
      "logps/rejected": -114.6706771850586,
      "loss": 0.28444111347198486,
      "nll_loss": 2.844240188598633,
      "rewards/accuracies": 1.0,
      "rewards/chosen": 10.005387306213379,
      "rewards/margins": 11.355799674987793,
      "rewards/rejected": -1.3504126071929932,
      "step": 7
    },
    {
      "epoch": 4.0,
      "grad_norm": 0.34319013357162476,
      "learning_rate": 4.698684378016222e-05,
      "logits/chosen": 1.028510332107544,
      "logits/rejected": 1.1937694549560547,
      "logps/chosen": -257.9039306640625,
      "logps/rejected": -111.61840057373047,
      "loss": 0.25356945395469666,
      "nll_loss": 2.535691738128662,
      "rewards/accuracies": 1.0,
      "rewards/chosen": 13.82034683227539,
      "rewards/margins": 16.24317169189453,
      "rewards/rejected": -2.4228243827819824,
      "step": 8
    },
    {
      "epoch": 4.5,
      "grad_norm": 0.3264783024787903,
      "learning_rate": 4.592916195656322e-05,
      "logits/chosen": 1.4608074426651,
      "logits/rejected": 1.6240922212600708,
      "logps/chosen": -286.8519287109375,
      "logps/rejected": -114.29640197753906,
      "loss": 0.2805436849594116,
      "nll_loss": 2.805433988571167,
      "rewards/accuracies": 1.0,
      "rewards/chosen": 15.604719161987305,
      "rewards/margins": 17.241561889648438,
      "rewards/rejected": -1.636841893196106,
      "step": 9
    },
    {
      "epoch": 5.0,
      "grad_norm": 0.2881050705909729,
      "learning_rate": 4.4728512734909844e-05,
      "logits/chosen": 1.1297067403793335,
      "logits/rejected": 1.4389699697494507,
      "logps/chosen": -209.1023712158203,
      "logps/rejected": -118.57534790039062,
      "loss": 0.21103455126285553,
      "nll_loss": 2.1103408336639404,
      "rewards/accuracies": 1.0,
      "rewards/chosen": 12.828682899475098,
      "rewards/margins": 15.623346328735352,
      "rewards/rejected": -2.794663906097412,
      "step": 10
    },
    {
      "epoch": 5.5,
      "grad_norm": 0.28840726613998413,
      "learning_rate": 4.3393097766828293e-05,
      "logits/chosen": 1.5240179300308228,
      "logits/rejected": 1.6537256240844727,
      "logps/chosen": -231.73692321777344,
      "logps/rejected": -104.76815795898438,
      "loss": 0.2420765906572342,
      "nll_loss": 2.4207653999328613,
      "rewards/accuracies": 1.0,
      "rewards/chosen": 15.80117416381836,
      "rewards/margins": 17.929916381835938,
      "rewards/rejected": -2.1287412643432617,
      "step": 11
    },
    {
      "epoch": 6.0,
      "grad_norm": 0.2765803337097168,
      "learning_rate": 4.193203929064353e-05,
      "logits/chosen": 1.499211311340332,
      "logits/rejected": 1.8360711336135864,
      "logps/chosen": -227.2552032470703,
      "logps/rejected": -131.73605346679688,
      "loss": 0.21334931254386902,
      "nll_loss": 2.1334917545318604,
      "rewards/accuracies": 1.0,
      "rewards/chosen": 16.328441619873047,
      "rewards/margins": 18.99445152282715,
      "rewards/rejected": -2.666008949279785,
      "step": 12
    },
    {
      "epoch": 6.5,
      "grad_norm": 0.2781386077404022,
      "learning_rate": 4.03553178172417e-05,
      "logits/chosen": 1.8178521394729614,
      "logits/rejected": 1.9007461071014404,
      "logps/chosen": -246.22056579589844,
      "logps/rejected": -110.68417358398438,
      "loss": 0.24077099561691284,
      "nll_loss": 2.407710075378418,
      "rewards/accuracies": 1.0,
      "rewards/chosen": 17.863698959350586,
      "rewards/margins": 19.48386573791504,
      "rewards/rejected": -1.6201684474945068,
      "step": 13
    },
    {
      "epoch": 7.0,
      "grad_norm": 0.2513338029384613,
      "learning_rate": 3.867370395306068e-05,
      "logits/chosen": 1.419611930847168,
      "logits/rejected": 1.8179534673690796,
      "logps/chosen": -184.7537384033203,
      "logps/rejected": -128.11627197265625,
      "loss": 0.18617191910743713,
      "nll_loss": 1.8617188930511475,
      "rewards/accuracies": 1.0,
      "rewards/chosen": 17.067703247070312,
      "rewards/margins": 20.471908569335938,
      "rewards/rejected": -3.404205083847046,
      "step": 14
    },
    {
      "epoch": 7.5,
      "grad_norm": 0.24078604578971863,
      "learning_rate": 3.689868482592684e-05,
      "logits/chosen": 1.5202300548553467,
      "logits/rejected": 1.4451717138290405,
      "logps/chosen": -186.9448699951172,
      "logps/rejected": -134.994873046875,
      "loss": 0.18625181913375854,
      "nll_loss": 1.8625178337097168,
      "rewards/accuracies": 1.0,
      "rewards/chosen": 17.45549774169922,
      "rewards/margins": 20.963037490844727,
      "rewards/rejected": -3.5075387954711914,
      "step": 15
    },
    {
      "epoch": 8.0,
      "grad_norm": 0.2641218602657318,
      "learning_rate": 3.504238561632424e-05,
      "logits/chosen": 1.7671902179718018,
      "logits/rejected": 2.350682258605957,
      "logps/chosen": -217.12744140625,
      "logps/rejected": -106.15504455566406,
      "loss": 0.21411478519439697,
      "nll_loss": 2.141148090362549,
      "rewards/accuracies": 1.0,
      "rewards/chosen": 20.166099548339844,
      "rewards/margins": 21.917882919311523,
      "rewards/rejected": -1.7517831325531006,
      "step": 16
    },
    {
      "epoch": 8.5,
      "grad_norm": 0.2480757236480713,
      "learning_rate": 3.311748673011709e-05,
      "logits/chosen": 1.6178916692733765,
      "logits/rejected": 1.9000247716903687,
      "logps/chosen": -204.7000732421875,
      "logps/rejected": -118.40432739257812,
      "loss": 0.193865105509758,
      "nll_loss": 1.9386509656906128,
      "rewards/accuracies": 1.0,
      "rewards/chosen": 19.592580795288086,
      "rewards/margins": 23.078105926513672,
      "rewards/rejected": -3.485527992248535,
      "step": 17
    },
    {
      "epoch": 9.0,
      "grad_norm": 0.23976729810237885,
      "learning_rate": 3.1137137178519985e-05,
      "logits/chosen": 1.5811121463775635,
      "logits/rejected": 1.8433393239974976,
      "logps/chosen": -177.70779418945312,
      "logps/rejected": -125.83042907714844,
      "loss": 0.1846872866153717,
      "nll_loss": 1.8468730449676514,
      "rewards/accuracies": 1.0,
      "rewards/chosen": 20.195463180541992,
      "rewards/margins": 22.277740478515625,
      "rewards/rejected": -2.082277297973633,
      "step": 18
    },
    {
      "epoch": 9.5,
      "grad_norm": 0.2394760102033615,
      "learning_rate": 2.9114864757018352e-05,
      "logits/chosen": 1.4372100830078125,
      "logits/rejected": 1.8667820692062378,
      "logps/chosen": -176.240478515625,
      "logps/rejected": -102.0673828125,
      "loss": 0.17548541724681854,
      "nll_loss": 1.7548539638519287,
      "rewards/accuracies": 1.0,
      "rewards/chosen": 20.510282516479492,
      "rewards/margins": 23.213382720947266,
      "rewards/rejected": -2.7030999660491943,
      "step": 19
    },
    {
      "epoch": 10.0,
      "grad_norm": 0.23995912075042725,
      "learning_rate": 2.7064483636808313e-05,
      "logits/chosen": 1.5910006761550903,
      "logits/rejected": 1.76851487159729,
      "logps/chosen": -185.51951599121094,
      "logps/rejected": -146.24314880371094,
      "loss": 0.18295589089393616,
      "nll_loss": 1.8295589685440063,
      "rewards/accuracies": 1.0,
      "rewards/chosen": 21.34255027770996,
      "rewards/margins": 24.61483383178711,
      "rewards/rejected": -3.2722816467285156,
      "step": 20
    },
    {
      "epoch": 10.5,
      "grad_norm": 0.23980359733104706,
      "learning_rate": 2.5e-05,
      "logits/chosen": 1.6856205463409424,
      "logits/rejected": 1.935638189315796,
      "logps/chosen": -185.94544982910156,
      "logps/rejected": -122.09562683105469,
      "loss": 0.19496451318264008,
      "nll_loss": 1.9496451616287231,
      "rewards/accuracies": 1.0,
      "rewards/chosen": 20.73805046081543,
      "rewards/margins": 23.83291244506836,
      "rewards/rejected": -3.0948615074157715,
      "step": 21
    },
    {
      "epoch": 11.0,
      "grad_norm": 0.24130310118198395,
      "learning_rate": 2.2935516363191693e-05,
      "logits/chosen": 1.1069573163986206,
      "logits/rejected": 1.5308476686477661,
      "logps/chosen": -157.90794372558594,
      "logps/rejected": -130.5032958984375,
      "loss": 0.14591673016548157,
      "nll_loss": 1.459167242050171,
      "rewards/accuracies": 1.0,
      "rewards/chosen": 22.905439376831055,
      "rewards/margins": 26.214797973632812,
      "rewards/rejected": -3.3093576431274414,
      "step": 22
    },
    {
      "epoch": 11.5,
      "grad_norm": 0.24958626925945282,
      "learning_rate": 2.088513524298165e-05,
      "logits/chosen": 1.6068215370178223,
      "logits/rejected": 1.8942545652389526,
      "logps/chosen": -185.63314819335938,
      "logps/rejected": -129.23275756835938,
      "loss": 0.19032619893550873,
      "nll_loss": 1.9032620191574097,
      "rewards/accuracies": 1.0,
      "rewards/chosen": 24.08209991455078,
      "rewards/margins": 25.450824737548828,
      "rewards/rejected": -1.3687264919281006,
      "step": 23
    },
    {
      "epoch": 12.0,
      "grad_norm": 0.2331785410642624,
      "learning_rate": 1.8862862821480025e-05,
      "logits/chosen": 0.9496405124664307,
      "logits/rejected": 1.4241453409194946,
      "logps/chosen": -142.03335571289062,
      "logps/rejected": -127.25737762451172,
      "loss": 0.1343969702720642,
      "nll_loss": 1.3439698219299316,
      "rewards/accuracies": 1.0,
      "rewards/chosen": 21.180082321166992,
      "rewards/margins": 26.60469627380371,
      "rewards/rejected": -5.424615859985352,
      "step": 24
    },
    {
      "epoch": 12.5,
      "grad_norm": 0.23167486488819122,
      "learning_rate": 1.6882513269882917e-05,
      "logits/chosen": 0.9223819971084595,
      "logits/rejected": 1.5592875480651855,
      "logps/chosen": -148.83151245117188,
      "logps/rejected": -120.81875610351562,
      "loss": 0.13860327005386353,
      "nll_loss": 1.3860325813293457,
      "rewards/accuracies": 1.0,
      "rewards/chosen": 23.887048721313477,
      "rewards/margins": 28.074344635009766,
      "rewards/rejected": -4.187295913696289,
      "step": 25
    },
    {
      "epoch": 13.0,
      "grad_norm": 0.24665434658527374,
      "learning_rate": 1.495761438367577e-05,
      "logits/chosen": 1.4035608768463135,
      "logits/rejected": 1.592110276222229,
      "logps/chosen": -165.41534423828125,
      "logps/rejected": -139.52828979492188,
      "loss": 0.17243248224258423,
      "nll_loss": 1.7243247032165527,
      "rewards/accuracies": 1.0,
      "rewards/chosen": 22.71709442138672,
      "rewards/margins": 25.708833694458008,
      "rewards/rejected": -2.9917383193969727,
      "step": 26
    },
    {
      "epoch": 13.5,
      "grad_norm": 0.24414831399917603,
      "learning_rate": 1.3101315174073162e-05,
      "logits/chosen": 1.2496869564056396,
      "logits/rejected": 1.5478211641311646,
      "logps/chosen": -147.55345153808594,
      "logps/rejected": -121.79801177978516,
      "loss": 0.16210804879665375,
      "nll_loss": 1.6210803985595703,
      "rewards/accuracies": 1.0,
      "rewards/chosen": 22.575027465820312,
      "rewards/margins": 24.645002365112305,
      "rewards/rejected": -2.069977283477783,
      "step": 27
    },
    {
      "epoch": 14.0,
      "grad_norm": 0.23758991062641144,
      "learning_rate": 1.1326296046939333e-05,
      "logits/chosen": 0.8038955330848694,
      "logits/rejected": 1.43307626247406,
      "logps/chosen": -154.92762756347656,
      "logps/rejected": -142.7965850830078,
      "loss": 0.13775420188903809,
      "nll_loss": 1.3775420188903809,
      "rewards/accuracies": 1.0,
      "rewards/chosen": 25.205698013305664,
      "rewards/margins": 30.73950958251953,
      "rewards/rejected": -5.533811569213867,
      "step": 28
    },
    {
      "epoch": 14.5,
      "grad_norm": 0.2509008049964905,
      "learning_rate": 9.644682182758306e-06,
      "logits/chosen": 1.2581326961517334,
      "logits/rejected": 1.571120023727417,
      "logps/chosen": -164.84486389160156,
      "logps/rejected": -132.17367553710938,
      "loss": 0.16873346269130707,
      "nll_loss": 1.6873347759246826,
      "rewards/accuracies": 1.0,
      "rewards/chosen": 24.35677146911621,
      "rewards/margins": 26.364137649536133,
      "rewards/rejected": -2.0073676109313965,
      "step": 29
    },
    {
      "epoch": 15.0,
      "grad_norm": 0.2378891259431839,
      "learning_rate": 8.067960709356478e-06,
      "logits/chosen": 0.5931491255760193,
      "logits/rejected": 1.265857458114624,
      "logps/chosen": -128.52427673339844,
      "logps/rejected": -135.16363525390625,
      "loss": 0.12185196578502655,
      "nll_loss": 1.218519687652588,
      "rewards/accuracies": 1.0,
      "rewards/chosen": 24.335145950317383,
      "rewards/margins": 30.20583724975586,
      "rewards/rejected": -5.870691776275635,
      "step": 30
    }
  ],
  "logging_steps": 1,
  "max_steps": 40,
  "num_input_tokens_seen": 0,
  "num_train_epochs": 20,
  "save_steps": 15,
  "stateful_callbacks": {
    "TrainerControl": {
      "args": {
        "should_epoch_stop": false,
        "should_evaluate": false,
        "should_log": false,
        "should_save": true,
        "should_training_stop": false
      },
      "attributes": {}
    }
  },
  "total_flos": 345239543808000.0,
  "train_batch_size": 1,
  "trial_name": null,
  "trial_params": null
}
